ptolemy_client-0.1.0b50.dist-info/METADATA
ptolemy_client-0.1.0b50.dist-info/WHEEL
ptolemy_client-0.1.0b50.dist-info/entry_points.txt
ptolemy_client.libs/libgcc_s-1e52349c.so.1
ptolemy_client/__init__.py
ptolemy_client/client.py
ptolemy_client/_core.pyi
ptolemy_client/tier.py
ptolemy_client/setup_dev.py
ptolemy_client/io.py
ptolemy_client/_core.abi3.so
ptolemy_client-0.1.0b50.dist-info/RECORD
