Metadata-Version: 2.4
Name: ptolemy-client
Version: 0.1.0b50
Requires-Dist: aiohttp>=3.11.10
Requires-Dist: pydantic>=2.10.4
Requires-Dist: questionary>=2.1.0
Requires-Dist: tenacity>=9.0.0
Requires-Dist: prompt-toolkit>=3.0.48
Requires-Dist: click>=8.1.8
Requires-Dist: tabulate>=0.9.0
Requires-Dist: pandas>=2.2.3
Summary: Add your description here
Author-email: Raz Besaleli <raz@besaleli.io>
Requires-Python: >=3.12
